lithium/__init__.py
lithium/__main__.py
lithium/py.typed
lithium/reducer.py
lithium/strategies.py
lithium/testcases.py
lithium/util.py
lithium/docs/algorithm.md
lithium/docs/creating-tests.md
lithium/docs/related.txt
lithium/docs/using-for-firefox.md
lithium/docs/examples/crash.c
lithium/docs/examples/arithmetic/11.txt
lithium/docs/examples/arithmetic/product_divides.py
lithium/interestingness/__init__.py
lithium/interestingness/crashes.py
lithium/interestingness/diff_test.py
lithium/interestingness/hangs.py
lithium/interestingness/outputs.py
lithium/interestingness/repeat.py
lithium/interestingness/timed_run.py
lithium/interestingness/utils.py
lithium_reducer-4.0.0.dist-info/LICENSE
lithium_reducer-4.0.0.dist-info/METADATA
lithium_reducer-4.0.0.dist-info/WHEEL
lithium_reducer-4.0.0.dist-info/entry_points.txt
lithium_reducer-4.0.0.dist-info/top_level.txt
lithium_reducer-4.0.0.dist-info/RECORD
