Metadata-Version: 2.1
Name: lithium-reducer
Version: 4.0.0
Summary: Lithium is an automated testcase reduction tool
Home-page: https://github.com/MozillaSecurity/lithium
Author: Jesse Ruderman
Maintainer: Mozilla Fuzzing Team
Maintainer-email: fuzzing@mozilla.com
License: MPL 2.0
Keywords: fuzz,fuzzing,reduce,reducer,reduction,security,test,testing
Classifier: Intended Audience :: Developers
Classifier: License :: OSI Approved :: Mozilla Public License 2.0 (MPL 2.0)
Classifier: Programming Language :: Python :: 3
Classifier: Topic :: Security
Classifier: Topic :: Software Development :: Testing
Requires-Python: >=3.8
License-File: LICENSE
Requires-Dist: ffpuppet>=0.11.2
Provides-Extra: dev
Requires-Dist: pre-commit; extra == "dev"
Requires-Dist: tox; extra == "dev"
